MANIFEST.in
README.md
setup.py
ciseau/__init__.py
ciseau/constants.py
ciseau/quoted_expressions.py
ciseau/regular_expressions.py
ciseau/sentence_tokenizer.py
ciseau/wiki_markup_processing.py
ciseau/word_tokenizer.py
ciseau.egg-info/PKG-INFO
ciseau.egg-info/SOURCES.txt
ciseau.egg-info/dependency_links.txt
ciseau.egg-info/not-zip-safe
ciseau.egg-info/top_level.txt