Metadata-Version: 1.1
Name: ciseau
Version: 1.0.1
Summary: Word and sentence tokenization.
Home-page: https://github.com/JonathanRaiman/ciseau
Author: Jonathan Raiman
Author-email: jonathanraiman@gmail.com
License: MIT
Download-URL: https://github.com/JonathanRaiman/ciseau
Keywords: XML,tokenization,NLP
Platform: any
Classifier: Intended Audience :: Science/Research
Classifier: Operating System :: OS Independent
Classifier: Programming Language :: Python :: 3.3
Classifier: Programming Language :: Python :: 2.7
Classifier: Topic :: Text Processing :: Linguistic
